GOSTurban/LEI.py
GOSTurban/UrbanRaster.py
GOSTurban/__init__.py
gosturban-1.0.0.dist-info/licenses/LICENSE
gosturban-1.0.0.dist-info/METADATA
gosturban-1.0.0.dist-info/WHEEL
gosturban-1.0.0.dist-info/top_level.txt
gosturban-1.0.0.dist-info/RECORD
