Metadata-Version: 2.4
Name: GOSTurban
Version: 1.0.0
Summary: Multiple functions, tools, and tutorials for calculating urbanization based on gridded population data
Author-email: World Bank <github@worldbank.org>
Maintainer-email: "Benjamin P. Stewart" <bstewart@worldbankgroup.org>, Andres Chamorro <achamorroelizond@worldbank.org>
License: MIT License
Project-URL: Homepage, https://github.com/worldbank/GOSTurban
Project-URL: Bug Reports, https://github.com/worldbank/GOSTurban/issues
Project-URL: Source, https://github.com/worldbank/GOSTurban
Keywords: gosturban,urban,raster
Classifier: Programming Language :: Python :: 3.8
Classifier: Programming Language :: Python :: 3.9
Classifier: Programming Language :: Python :: 3.10
Classifier: Programming Language :: Python :: 3.11
Classifier: Programming Language :: Python :: 3 :: Only
Classifier: License :: OSI Approved :: MIT License
Classifier: Development Status :: 3 - Alpha
Classifier: Intended Audience :: Developers
Classifier: Operating System :: OS Independent
Classifier: Topic :: Scientific/Engineering
Requires-Python: >=3.8
License-File: LICENSE
Requires-Dist: rasterio
Requires-Dist: geopandas
Requires-Dist: pandas
Requires-Dist: numpy
Requires-Dist: scipy
Requires-Dist: shapely
Requires-Dist: geopy
Requires-Dist: pyproj
Requires-Dist: elevation
Requires-Dist: geojson
Provides-Extra: dev
Requires-Dist: pytest; extra == "dev"
Requires-Dist: pytest-cov; extra == "dev"
Requires-Dist: docutils==0.17.1; extra == "dev"
Requires-Dist: jupyter-book; extra == "dev"
Requires-Dist: sphinxcontrib-apidoc<1,>=0.4.0; extra == "dev"
Requires-Dist: jupyter-cache>=0.6.0; extra == "dev"
Requires-Dist: nbconvert; extra == "dev"
Requires-Dist: nbstripout; extra == "dev"
Dynamic: license-file
